cover_rage_client
