Metadata-Version: 1.1
Name: cover-rage-client
Version: 0.0.9
Summary: Utility (client) to check coverage for the last commit / pull request while running tests on CI.
Home-page: https://github.com/alexryabtsev/cover_rage_client
Author: Alexander Ryabtsev
Author-email: ryabtsev.alexander@gmail.com
License: MIT
Platform: UNKNOWN
Classifier: b'Development Status :: 3 - Alpha'
Classifier: b'Environment :: Console'
Classifier: b'Intended Audience :: Developers'
Classifier: b'License :: OSI Approved :: MIT License'
Classifier: b'Natural Language :: English'
Classifier: b'Operating System :: OS Independent'
Classifier: b'Programming Language :: Python'
Classifier: b'Programming Language :: Python :: 3.5'
Classifier: b'Topic :: Software Development :: Testing'
